sauerkraut/CMakeLists.txt
sauerkraut/__init__.py
sauerkraut/_sauerkraut.so
sauerkraut/greenlet_compat.so
sauerkraut/liveness.py
sauerkraut/sauerkraut.C
sauerkraut/serdes.so
sauerkraut/buffer/CMakeLists.txt
sauerkraut/buffer/code_unit.fbs
sauerkraut/buffer/py_code_object.fbs
sauerkraut/buffer/py_frame.fbs
sauerkraut/buffer/py_interpreter_frame.fbs
sauerkraut/buffer/py_object.fbs
sauerkraut/buffer/py_object_head.fbs
sauerkraut/buffer/py_var_object_head.fbs
sauerkraut/buffer/stackref.fbs
sauerkraut/buffer/include/offsets.h
sauerkraut/greenlet_compat/CMakeLists.txt
sauerkraut/greenlet_compat/greenlet_compat.C
sauerkraut/greenlet_compat/include/greenlet_compat.h
sauerkraut/include/py_structs.h
sauerkraut/include/pyref.h
sauerkraut/include/sauerkraut_cpython_compat.h
sauerkraut/include/utils.h
sauerkraut/serdes/CMakeLists.txt
sauerkraut/serdes/serdes.C
sauerkraut/serdes/include/serdes.h
sauerkraut-0.1.0.dist-info/licenses/LICENSE
sauerkraut-0.1.0.dist-info/METADATA
sauerkraut-0.1.0.dist-info/WHEEL
sauerkraut-0.1.0.dist-info/top_level.txt
sauerkraut-0.1.0.dist-info/RECORD
