Metadata-Version: 2.4
Name: sauerkraut
Version: 0.1.0
Summary: Serialization for Python's Control State
Author: Zane Fink
Author-email: Zane Fink <zanef2@illinois.edu>
License: Apache-2.0 WITH LLVM-exception
Project-URL: Homepage, https://github.com/UIUC-PPL/sauerkraut
Project-URL: Repository, https://github.com/UIUC-PPL/sauerkraut
Project-URL: Issues, https://github.com/UIUC-PPL/sauerkraut/issues
Keywords: serialization,pickle,greenlet,coroutine,checkpoint,migration
Classifier: Development Status :: 3 - Alpha
Classifier: Intended Audience :: Developers
Classifier: Intended Audience :: Science/Research
Classifier: License :: OSI Approved :: Apache Software License
Classifier: Programming Language :: Python :: 3.13
Classifier: Programming Language :: Python :: 3.14
Classifier: Programming Language :: C++
Classifier: Operating System :: POSIX :: Linux
Classifier: Operating System :: MacOS
Classifier: Topic :: Software Development :: Libraries :: Python Modules
Classifier: Topic :: System :: Distributed Computing
Requires-Python: >=3.13
License-File: LICENSE
Requires-Dist: bytecode
Requires-Dist: numpy
Dynamic: author
Dynamic: license-file
Dynamic: requires-python
